pyfile_utils/__init__.py
pyfile_utils/_version.py
pyfile_utils/auto_init.py
pyfile_utils/config.py
pyfile_utils/git.py
pyfile_utils/output.py
pyfile_utils/savenload.py
pyfile_utils-1.0.5.dist-info/LICENSE
pyfile_utils-1.0.5.dist-info/METADATA
pyfile_utils-1.0.5.dist-info/WHEEL
pyfile_utils-1.0.5.dist-info/top_level.txt
pyfile_utils-1.0.5.dist-info/zip-safe
pyfile_utils-1.0.5.dist-info/RECORD
