Metadata-Version: 2.1
Name: pyfile-utils
Version: 1.0.5
Summary: A collection of utils for file write/load and instantiation
Home-page: https://github.com/mir-group/PyfileUtils
Author: Lixin Sun
Author-email: nw13mifaso@gmail.com
License: UNKNOWN
Platform: UNKNOWN
Classifier: Programming Language :: Python :: 3
Classifier: License :: OSI Approved :: MIT License
Classifier: Operating System :: OS Independent
Requires-Python: >=3.6.9
License-File: LICENSE
Requires-Dist: numpy
Requires-Dist: pyyaml
Requires-Dist: contextvars
